ktx/__init__.py
ktx/_meta.py
ktx/abc.py
ktx/bind.py
ktx/ctx.py
ktx/ktxid.py
ktx/log.py
ktx/py.typed
ktx/user.py
ktx/vars.py
ktx/adapters/__init__.py
ktx/adapters/sentry.py
ktx-0.4.0.dist-info/licenses/LICENSE
ktx-0.4.0.dist-info/METADATA
ktx-0.4.0.dist-info/WHEEL
ktx-0.4.0.dist-info/top_level.txt
ktx-0.4.0.dist-info/RECORD
