Metadata-Version: 2.4
Name: ktx
Version: 0.4.0
Summary: context library
Author-email: KTS <hello@kts.tech>
License:                                  Apache License
Classifier: Development Status :: 5 - Production/Stable
Classifier: Framework :: AsyncIO
Classifier: Operating System :: POSIX
Classifier: Operating System :: MacOS :: MacOS X
Classifier: Operating System :: Microsoft :: Windows
Classifier: Programming Language :: Python :: 3.10
Classifier: Programming Language :: Python :: 3.11
Classifier: Programming Language :: Python :: 3.12
Classifier: Intended Audience :: Developers
Classifier: Topic :: Software Development :: Libraries :: Python Modules
Requires-Python: >=3.10.0
License-File: LICENSE
Requires-Dist: immutabledict
Requires-Dist: typing-extensions; python_version < "3.11"
Provides-Extra: sentry
Requires-Dist: sentry-sdk>=2.11.0; extra == "sentry"
Provides-Extra: test
Requires-Dist: coverage>=7.6.1; extra == "test"
Requires-Dist: pytest; extra == "test"
Requires-Dist: mypy; extra == "test"
Requires-Dist: ruff; extra == "test"
Requires-Dist: deptry; extra == "test"
Dynamic: license-file
